scab/__init__.py
scab/io.py
scab/pl.py
scab/pp.py
scab/tl.py
scab/ut.py
scab/vdj.py
scab/version.py
scab/cellranger/README.md
scab/cellranger/__init__.py
scab/cellranger/example.yaml
scab/cellranger/index_sequences.csv
scab/cellranger/scabranger.py
scab/models/__init__.py
scab/models/lineage.py
scab/ont/__init__.py
scab/ont/barcodes.py
scab/ont/consensus.py
scab/ont/vdj.py
scab/ont/whitelists/737K-august-2016.txt.gz
scab/plots/__init__.py
scab/plots/bar.py
scab/plots/heatmap.py
scab/plots/kde.py
scab/plots/qc.py
scab/plots/ridge.py
scab/plots/scatter.py
scab/plots/umap.py
scab/scripts/__init__.py
scab/scripts/scab.py
scab/tests/__init__.py
scab/tests/test_batch_correction.py
scab/tests/test_cellhashes.py
scab/tests/test_embeddings.py
scab/tests/test_io.py
scab/tests/test_ont_vdj.py
scab/tools/__init__.py
scab/tools/batch_correction.py
scab/tools/cellhashes.py
scab/tools/clonify.py
scab/tools/embeddings.py
scab/tools/similarity.py
scab/tools/specificity.py
scab-0.2.4.data/scripts/batch_cellranger
scab-0.2.4.data/scripts/scabranger
scab-0.2.4.dist-info/licenses/LICENSE
scab-0.2.4.dist-info/METADATA
scab-0.2.4.dist-info/WHEEL
scab-0.2.4.dist-info/entry_points.txt
scab-0.2.4.dist-info/top_level.txt
scab-0.2.4.dist-info/RECORD
