Metadata-Version: 2.4
Name: scab
Version: 0.2.4
Summary: Single cell analysis of B cells
Home-page: https://github.com/brineylab/scab
Author: Bryan Briney
Author-email: briney@scripps.edu
Classifier: Development Status :: 5 - Production/Stable
Classifier: Intended Audience :: Science/Research
Classifier: License :: OSI Approved :: MIT License
Classifier: Operating System :: OS Independent
Classifier: Programming Language :: Python :: 3
Classifier: Programming Language :: Python :: 3.8
Classifier: Programming Language :: Python :: 3.9
Classifier: Programming Language :: Python :: 3.10
Classifier: Programming Language :: Python :: 3.11
Classifier: Topic :: Scientific/Engineering :: Bio-Informatics
Requires-Python: >=3.8
License-File: LICENSE
Requires-Dist: abstar>=0.7.1
Requires-Dist: abutils>=0.5.2
Requires-Dist: anndata
Requires-Dist: click
Requires-Dist: dnachisel
Requires-Dist: fastcluster
Requires-Dist: harmonypy
Requires-Dist: humanize
Requires-Dist: leidenalg
Requires-Dist: matplotlib
Requires-Dist: mnemonic
Requires-Dist: natsort
Requires-Dist: numpy
Requires-Dist: pandas
Requires-Dist: prettytable
Requires-Dist: pytest
Requires-Dist: python-Levenshtein
Requires-Dist: pyyaml
Requires-Dist: sample-sheet
Requires-Dist: scanpy
Requires-Dist: scanorama
Requires-Dist: scipy
Requires-Dist: scrublet
Requires-Dist: scvelo
Requires-Dist: seaborn>=0.11
Requires-Dist: umap-learn
Dynamic: author
Dynamic: author-email
Dynamic: classifier
Dynamic: description
Dynamic: description-content-type
Dynamic: home-page
Dynamic: license-file
Dynamic: requires-dist
Dynamic: requires-python
Dynamic: summary
